tropopause/__init__.py
tropopause-0.10.0.dist-info/LICENSE
tropopause-0.10.0.dist-info/METADATA
tropopause-0.10.0.dist-info/WHEEL
tropopause-0.10.0.dist-info/top_level.txt
tropopause-0.10.0.dist-info/zip-safe
tropopause-0.10.0.dist-info/RECORD
