Metadata-Version: 2.1
Name: tropopause
Version: 0.10.0
Summary: Extra utilities for troposphere
Home-page: http://github.com/hstack/tropopause
Author: Andrei Dragomir
Author-email: adragomir@gmail.com
License: MIT
Platform: UNKNOWN
Classifier: Development Status :: 3 - Alpha
Classifier: License :: OSI Approved :: MIT License
Classifier: Programming Language :: Python :: 2.7
Requires-Dist: troposphere (>=1.9.2)
